dc_datareader_connector/__init__.py
dc_datareader_connector/datareader_connector.py
dc_datareader_connector/datareader_xml_connector.py
dc_datareader_connector-1.0.0.dist-info/METADATA
dc_datareader_connector-1.0.0.dist-info/WHEEL
dc_datareader_connector-1.0.0.dist-info/top_level.txt
dc_datareader_connector-1.0.0.dist-info/RECORD
