Metadata-Version: 2.1
Name: dc-datareader-connector
Version: 1.0.0
Summary: Datareader Connector
Home-page: UNKNOWN
Author: Calyx
License: UNKNOWN
Platform: UNKNOWN
